odoo/addons/sale_order_partner_no_autofollow/README.rst
odoo/addons/sale_order_partner_no_autofollow/__init__.py
odoo/addons/sale_order_partner_no_autofollow/__manifest__.py
odoo/addons/sale_order_partner_no_autofollow/i18n/it.po
odoo/addons/sale_order_partner_no_autofollow/i18n/sale_order_partner_no_autofollow.pot
odoo/addons/sale_order_partner_no_autofollow/models/__init__.py
odoo/addons/sale_order_partner_no_autofollow/models/res_config_settings.py
odoo/addons/sale_order_partner_no_autofollow/models/sale_order.py
odoo/addons/sale_order_partner_no_autofollow/readme/CONFIGURE.md
odoo/addons/sale_order_partner_no_autofollow/readme/DESCRIPTION.md
odoo/addons/sale_order_partner_no_autofollow/static/description/icon.png
odoo/addons/sale_order_partner_no_autofollow/static/description/index.html
odoo/addons/sale_order_partner_no_autofollow/tests/__init__.py
odoo/addons/sale_order_partner_no_autofollow/tests/common.py
odoo/addons/sale_order_partner_no_autofollow/tests/test_no_autofollow_disabled.py
odoo/addons/sale_order_partner_no_autofollow/tests/test_no_autofollow_enabled.py
odoo/addons/sale_order_partner_no_autofollow/views/res_config_settings.xml
odoo_addon_sale_order_partner_no_autofollow-17.0.1.0.0.2.dist-info/METADATA
odoo_addon_sale_order_partner_no_autofollow-17.0.1.0.0.2.dist-info/WHEEL
odoo_addon_sale_order_partner_no_autofollow-17.0.1.0.0.2.dist-info/top_level.txt
odoo_addon_sale_order_partner_no_autofollow-17.0.1.0.0.2.dist-info/RECORD
